seqconf/__init__.py
seqconf/_base.py
seqconf-0.1.0.dist-info/LICENSE
seqconf-0.1.0.dist-info/METADATA
seqconf-0.1.0.dist-info/WHEEL
seqconf-0.1.0.dist-info/top_level.txt
seqconf-0.1.0.dist-info/RECORD
